nec_beamer/__init__.py
nec_beamer/nec_beamer.py
nec_beamer-0.1.4.data/scripts/nec_beamer
nec_beamer-0.1.4.dist-info/LICENSE
nec_beamer-0.1.4.dist-info/METADATA
nec_beamer-0.1.4.dist-info/WHEEL
nec_beamer-0.1.4.dist-info/top_level.txt
nec_beamer-0.1.4.dist-info/RECORD
