Metadata-Version: 2.1
Name: nec-beamer
Version: 0.1.4
Summary: NEC Beamer Web Interface Wrapper
Home-page: https://github.com/heinrich-foto/nec_beamer
Author: Heinrich-Foto
Author-email: nec_beamer@heinrich-foto.de
License: MIT
License-File: LICENSE
Requires-Dist: requests
Requires-Dist: click
